memorywrap/__init__.py
memorywrap/memory.py
memorywrap-1.1.7.dist-info/METADATA
memorywrap-1.1.7.dist-info/WHEEL
memorywrap-1.1.7.dist-info/top_level.txt
memorywrap-1.1.7.dist-info/RECORD
