Metadata-Version: 2.1
Name: memorywrap
Version: 1.1.7
Summary: Memory Wrap: an extension for image classification models
Author: La Rosa Biagio
Author-email: larosa@diag.uniroma1.it
Classifier: Programming Language :: Python :: 3
Classifier: License :: OSI Approved :: MIT License
Classifier: Operating System :: OS Independent
Requires-Dist: entmax
Requires-Dist: torch (>1.5)
